{
  "code": "E07000103",
  "name": "Watford",
  "type": "lad",
  "area": 2142.48,
  "count": 331,
  "parents": [
    {
      "code": "E10000015",
      "name": "Hertfordshire",
      "type": "cty"
    },
    {
      "code": "E12000006",
      "name": "East",
      "type": "rgn"
    },
    {
      "code": "E92000001",
      "name": "England",
      "type": "ctry"
    },
    {
      "code": "K04000001",
      "name": "England and Wales",
      "type": "ew"
    }
  ],
  "children": [
    {
      "code": "E02004968",
      "name": "Watford 001",
      "type": "msoa"
    },
    {
      "code": "E02004969",
      "name": "Watford 002",
      "type": "msoa"
    },
    {
      "code": "E02004970",
      "name": "Watford 003",
      "type": "msoa"
    },
    {
      "code": "E02004971",
      "name": "Watford 004",
      "type": "msoa"
    },
    {
      "code": "E02004972",
      "name": "Watford 005",
      "type": "msoa"
    },
    {
      "code": "E02004973",
      "name": "Watford 006",
      "type": "msoa"
    },
    {
      "code": "E02004974",
      "name": "Watford 007",
      "type": "msoa"
    },
    {
      "code": "E02004975",
      "name": "Watford 008",
      "type": "msoa"
    },
    {
      "code": "E02004976",
      "name": "Watford 009",
      "type": "msoa"
    },
    {
      "code": "E02004977",
      "name": "Watford 010",
      "type": "msoa"
    },
    {
      "code": "E02004978",
      "name": "Watford 011",
      "type": "msoa"
    },
    {
      "code": "E02004979",
      "name": "Watford 012",
      "type": "msoa"
    }
  ],
  "bounds": [
    [
      -0.43956,
      51.63711
    ],
    [
      -0.36879,
      51.70194
    ]
  ],
  "data": {
    "population": {
      "perc": {
        "2001": {
          "female": 50.8,
          "male": 49.2
        },
        "2011": {
          "female": 50.36,
          "male": 49.64
        },
        "change": {
          "female": -0.44,
          "male": 0.44
        }
      },
      "perc_rank": {
        "2001": {
          "female": 256.0,
          "male": 74.0
        },
        "2011": {
          "female": 282.0,
          "male": 46.0
        },
        "change": {
          "female": 196.0,
          "male": 131.0
        }
      },
      "value": {
        "2001": {
          "all": 79726.0,
          "female": 40499.0,
          "male": 39227.0
        },
        "2011": {
          "all": 90301.0,
          "female": 45473.0,
          "male": 44828.0
        },
        "change": {
          "all": 13.26,
          "female": 12.28,
          "male": 14.28
        }
      },
      "value_rank": {
        "2001": {
          "all": 286.0,
          "female": 290.0,
          "male": 283.0
        },
        "2011": {
          "all": 273.0,
          "female": 275.0,
          "male": 269.0
        },
        "change": {
          "all": 41.0,
          "female": 37.0,
          "male": 43.0
        }
      }
    },
    "religion": {
      "perc": {
        "2001": {
          "Buddhist": 0.33,
          "Christian": 66.45,
          "Hindu": 1.73,
          "Jewish": 1.12,
          "Muslim": 6.11,
          "No religion": 16.1,
          "Other religion": 0.36,
          "Religion not stated": 7.31,
          "Sikh": 0.49
        },
        "2011": {
          "Buddhist": 0.73,
          "Christian": 54.14,
          "Hindu": 4.82,
          "Jewish": 1.13,
          "Muslim": 9.86,
          "No religion": 21.41,
          "Other religion": 0.54,
          "Religion not stated": 6.74,
          "Sikh": 0.63
        },
        "change": {
          "Buddhist": 0.4,
          "Christian": -12.31,
          "Hindu": 3.09,
          "Jewish": 0.01,
          "Muslim": 3.75,
          "No religion": 5.31,
          "Other religion": 0.18,
          "Religion not stated": -0.57,
          "Sikh": 0.14
        }
      },
      "perc_rank": {
        "2001": {
          "Buddhist": 57.0,
          "Christian": 280.0,
          "Hindu": 37.0,
          "Jewish": 20.0,
          "Muslim": 34.0,
          "No religion": 110.0,
          "Other religion": 62.0,
          "Religion not stated": 197.0,
          "Sikh": 57.0
        },
        "2011": {
          "Buddhist": 36.0,
          "Christian": 276.0,
          "Hindu": 15.0,
          "Jewish": 20.0,
          "Muslim": 33.0,
          "No religion": 267.0,
          "Other religion": 45.0,
          "Religion not stated": 229.0,
          "Sikh": 61.0
        },
        "change": {
          "Buddhist": 15.0,
          "Christian": 155.0,
          "Hindu": 5.0,
          "Jewish": 50.0,
          "Muslim": 26.0,
          "No religion": 312.0,
          "Other religion": 58.0,
          "Religion not stated": 199.0,
          "Sikh": 54.0
        }
      },
      "value": {
        "2001": {
          "Buddhist": 262.0,
          "Christian": 52977.0,
          "Hindu": 1381.0,
          "Jewish": 892.0,
          "Muslim": 4869.0,
          "No religion": 12838.0,
          "Other religion": 290.0,
          "Religion not stated": 5825.0,
          "Sikh": 392.0,
          "all": 79726.0
        },
        "2011": {
          "Buddhist": 659.0,
          "Christian": 48891.0,
          "Hindu": 4348.0,
          "Jewish": 1023.0,
          "Muslim": 8905.0,
          "No religion": 19330.0,
          "Other religion": 489.0,
          "Religion not stated": 6090.0,
          "Sikh": 566.0,
          "all": 90301.0
        },
        "change": {
          "Buddhist": 151.53,
          "Christian": -7.71,
          "Hindu": 214.84,
          "Jewish": 14.69,
          "Muslim": 82.89,
          "No religion": 50.57,
          "Other religion": 68.62,
          "Religion not stated": 4.55,
          "Sikh": 44.39,
          "all": 13.26
        }
      },
      "value_rank": {
        "2001": {
          "Buddhist": 151.0,
          "Christian": 309.0,
          "Hindu": 70.0,
          "Jewish": 45.0,
          "Muslim": 68.0,
          "No religion": 246.0,
          "Other religion": 195.0,
          "Religion not stated": 281.0,
          "Sikh": 93.0,
          "all": 286.0
        },
        "2011": {
          "Buddhist": 103.0,
          "Christian": 300.0,
          "Hindu": 41.0,
          "Jewish": 40.0,
          "Muslim": 69.0,
          "No religion": 290.0,
          "Other religion": 189.0,
          "Religion not stated": 283.0,
          "Sikh": 88.0,
          "all": 273.0
        },
        "change": {
          "Buddhist": 28.0,
          "Christian": 66.0,
          "Hindu": 17.0,
          "Jewish": 84.0,
          "Muslim": 158.0,
          "No religion": 307.0,
          "Other religion": 145.0,
          "Religion not stated": 148.0,
          "Sikh": 130.0,
          "all": 41.0
        }
      }
    },
    "household": {
      "perc": {
        "2001": {
          "CohabitNKids": 7.85,
          "CohabitWKids": 3.57,
          "LoneNKids": 3.76,
          "LoneWKids": 5.95,
          "MarriedNKids": 25.19,
          "MarriedWKids": 20.24,
          "MultiOther": 3.63,
          "MultiStudents": 0.17,
          "OnePerson": 29.66
        },
        "2011": {
          "CohabitNKids": 7.26,
          "CohabitWKids": 4.01,
          "LoneNKids": 3.86,
          "LoneWKids": 7.92,
          "MarriedNKids": 21.91,
          "MarriedWKids": 20.15,
          "MultiOther": 3.69,
          "MultiStudents": 0.13,
          "OnePerson": 31.06
        },
        "change": {
          "CohabitNKids": -0.59,
          "CohabitWKids": 0.44,
          "LoneNKids": 0.1,
          "LoneWKids": 1.97,
          "MarriedNKids": -3.28,
          "MarriedWKids": -0.09,
          "MultiOther": 0.06,
          "MultiStudents": -0.04,
          "OnePerson": 1.4
        }
      },
      "perc_rank": {
        "2001": {
          "CohabitNKids": 12.0,
          "CohabitWKids": 124.0,
          "LoneNKids": 58.0,
          "LoneWKids": 186.0,
          "MarriedNKids": 283.0,
          "MarriedWKids": 113.0,
          "MultiOther": 38.0,
          "MultiStudents": 97.0,
          "OnePerson": 121.0
        },
        "2011": {
          "CohabitNKids": 92.0,
          "CohabitWKids": 226.0,
          "LoneNKids": 106.0,
          "LoneWKids": 126.0,
          "MarriedNKids": 291.0,
          "MarriedWKids": 40.0,
          "MultiOther": 44.0,
          "MultiStudents": 118.0,
          "OnePerson": 99.0
        },
        "change": {
          "CohabitNKids": 329.0,
          "CohabitWKids": 302.0,
          "LoneNKids": 307.0,
          "LoneWKids": 14.0,
          "MarriedNKids": 320.0,
          "MarriedWKids": 36.0,
          "MultiOther": 221.0,
          "MultiStudents": 307.0,
          "OnePerson": 101.0
        }
      },
      "value": {
        "2001": {
          "CohabitNKids": 2540.0,
          "CohabitWKids": 1154.0,
          "LoneNKids": 1215.0,
          "LoneWKids": 1924.0,
          "MarriedNKids": 8148.0,
          "MarriedWKids": 6548.0,
          "MultiOther": 1173.0,
          "MultiStudents": 54.0,
          "OnePerson": 9594.0,
          "all": 32350.0
        },
        "2011": {
          "CohabitNKids": 2664.0,
          "CohabitWKids": 1472.0,
          "LoneNKids": 1417.0,
          "LoneWKids": 2904.0,
          "MarriedNKids": 8038.0,
          "MarriedWKids": 7391.0,
          "MultiOther": 1354.0,
          "MultiStudents": 49.0,
          "OnePerson": 11392.0,
          "all": 36681.0
        },
        "change": {
          "CohabitNKids": 4.88,
          "CohabitWKids": 27.56,
          "LoneNKids": 16.63,
          "LoneWKids": 50.94,
          "MarriedNKids": -1.35,
          "MarriedWKids": 12.87,
          "MultiOther": 15.43,
          "MultiStudents": -9.26,
          "OnePerson": 18.74,
          "all": 13.39
        }
      },
      "value_rank": {
        "2001": {
          "CohabitNKids": 202.0,
          "CohabitWKids": 274.0,
          "LoneNKids": 240.0,
          "LoneWKids": 272.0,
          "MarriedNKids": 318.0,
          "MarriedWKids": 281.0,
          "MultiOther": 138.0,
          "MultiStudents": 125.0,
          "OnePerson": 268.0,
          "all": 291.0
        },
        "2011": {
          "CohabitNKids": 261.0,
          "CohabitWKids": 288.0,
          "LoneNKids": 258.0,
          "LoneWKids": 232.0,
          "MarriedNKids": 321.0,
          "MarriedWKids": 224.0,
          "MultiOther": 147.0,
          "MultiStudents": 131.0,
          "OnePerson": 259.0,
          "all": 279.0
        },
        "change": {
          "CohabitNKids": 316.0,
          "CohabitWKids": 269.0,
          "LoneNKids": 263.0,
          "LoneWKids": 8.0,
          "MarriedNKids": 246.0,
          "MarriedWKids": 19.0,
          "MultiOther": 191.0,
          "MultiStudents": 251.0,
          "OnePerson": 30.0,
          "all": 25.0
        }
      }
    },
    "ethnicity": {
      "perc": {
        "2001": {
          "asian": 8.78,
          "black": 2.66,
          "mixed": 2.1,
          "other": 0.5,
          "white": 85.95
        },
        "2011": {
          "asian": 17.91,
          "black": 5.79,
          "mixed": 3.44,
          "other": 0.94,
          "white": 71.92
        },
        "change": {
          "asian": 9.13,
          "black": 3.13,
          "mixed": 1.34,
          "other": 0.44,
          "white": -14.03
        }
      },
      "perc_rank": {
        "2001": {
          "asian": 36.0,
          "black": 38.0,
          "mixed": 40.0,
          "other": 51.0,
          "white": 288.0
        },
        "2011": {
          "asian": 23.0,
          "black": 41.0,
          "mixed": 43.0,
          "other": 70.0,
          "white": 295.0
        },
        "change": {
          "asian": 8.0,
          "black": 18.0,
          "mixed": 40.0,
          "other": 79.0,
          "white": 321.0
        }
      },
      "value": {
        "2001": {
          "all": 79726.0,
          "asian": 7001.0,
          "black": 2124.0,
          "mixed": 1673.0,
          "other": 402.0,
          "white": 68526.0
        },
        "2011": {
          "all": 90301.0,
          "asian": 16170.0,
          "black": 5229.0,
          "mixed": 3104.0,
          "other": 852.0,
          "white": 64946.0
        },
        "change": {
          "all": 13.26,
          "asian": 130.97,
          "black": 146.19,
          "mixed": 85.53,
          "other": 111.94,
          "white": -5.22
        }
      },
      "value_rank": {
        "2001": {
          "all": 286.0,
          "asian": 77.0,
          "black": 62.0,
          "mixed": 98.0,
          "other": 108.0,
          "white": 309.0
        },
        "2011": {
          "all": 273.0,
          "asian": 64.0,
          "black": 60.0,
          "mixed": 98.0,
          "other": 113.0,
          "white": 311.0
        },
        "change": {
          "all": 41.0,
          "asian": 98.0,
          "black": 97.0,
          "mixed": 188.0,
          "other": 129.0,
          "white": 304.0
        }
      }
    },
    "health": {
      "perc": {
        "2001": {
          "bad": 6.85,
          "fair": 20.59,
          "good": 72.57
        },
        "2011": {
          "bad": 4.14,
          "fair": 10.98,
          "good": 84.89
        },
        "change": {
          "bad": -2.71,
          "fair": -9.61,
          "good": 12.32
        }
      },
      "perc_rank": {
        "2001": {
          "bad": 274.0,
          "fair": 269.0,
          "good": 56.0
        },
        "2011": {
          "bad": 260.0,
          "fair": 290.0,
          "good": 47.0
        },
        "change": {
          "bad": 65.0,
          "fair": 269.0,
          "good": 160.0
        }
      },
      "value": {
        "2001": {
          "all": 79726.0,
          "bad": 5459.0,
          "fair": 16413.0,
          "good": 57854.0
        },
        "2011": {
          "all": 90301.0,
          "bad": 3737.0,
          "fair": 9911.0,
          "good": 76653.0
        },
        "change": {
          "all": 13.26,
          "bad": -31.54,
          "fair": -39.61,
          "good": 32.49
        }
      },
      "value_rank": {
        "2001": {
          "all": 286.0,
          "bad": 302.0,
          "fair": 297.0,
          "good": 274.0
        },
        "2011": {
          "all": 273.0,
          "bad": 297.0,
          "fair": 303.0,
          "good": 260.0
        },
        "change": {
          "all": 41.0,
          "bad": 63.0,
          "fair": 266.0,
          "good": 53.0
        }
      }
    },
    "economic": {
      "perc": {
        "2001": {
          "employee": 60.54,
          "inactive": 25.71,
          "self-employed": 8.56,
          "student": 2.72,
          "unemployed": 2.48
        },
        "2011": {
          "employee": 58.71,
          "inactive": 23.41,
          "self-employed": 10.4,
          "student": 3.42,
          "unemployed": 4.06
        },
        "change": {
          "employee": -1.83,
          "inactive": -2.3,
          "self-employed": 1.84,
          "student": 0.7,
          "unemployed": 1.58
        }
      },
      "perc_rank": {
        "2001": {
          "employee": 15.0,
          "inactive": 317.0,
          "self-employed": 173.0,
          "student": 79.0,
          "unemployed": 211.0
        },
        "2011": {
          "employee": 20.0,
          "inactive": 322.0,
          "self-employed": 145.0,
          "student": 83.0,
          "unemployed": 152.0
        },
        "change": {
          "employee": 287.0,
          "inactive": 130.0,
          "self-employed": 44.0,
          "student": 106.0,
          "unemployed": 38.0
        }
      },
      "value": {
        "2001": {
          "all": 58204.0,
          "employee": 35234.0,
          "inactive": 14963.0,
          "self-employed": 4984.0,
          "student": 1581.0,
          "unemployed": 1442.0
        },
        "2011": {
          "all": 66285.0,
          "employee": 38915.0,
          "inactive": 15515.0,
          "self-employed": 6894.0,
          "student": 2269.0,
          "unemployed": 2692.0
        },
        "change": {
          "all": 13.88,
          "employee": 10.45,
          "inactive": 3.69,
          "self-employed": 38.32,
          "student": 43.52,
          "unemployed": 86.69
        }
      },
      "value_rank": {
        "2001": {
          "all": 281.0,
          "employee": 254.0,
          "inactive": 311.0,
          "self-employed": 286.0,
          "student": 227.0,
          "unemployed": 271.0
        },
        "2011": {
          "all": 269.0,
          "employee": 247.0,
          "inactive": 306.0,
          "self-employed": 260.0,
          "student": 203.0,
          "unemployed": 224.0
        },
        "change": {
          "all": 44.0,
          "employee": 107.0,
          "inactive": 67.0,
          "self-employed": 42.0,
          "student": 113.0,
          "unemployed": 14.0
        }
      }
    },
    "travel": {
      "perc": {
        "2001": {
          "bicycle": 2.05,
          "bus": 5.66,
          "car_van": 66.75,
          "foot": 11.71,
          "home": 6.6,
          "moto": 1.0,
          "other": 0.24,
          "taxi": 0.46,
          "train_metro": 5.54
        },
        "2011": {
          "bicycle": 2.28,
          "bus": 4.77,
          "car_van": 57.43,
          "foot": 13.87,
          "home": 4.36,
          "moto": 0.82,
          "other": 0.58,
          "taxi": 0.46,
          "train_metro": 15.45
        },
        "change": {
          "bicycle": 0.23,
          "bus": -0.89,
          "car_van": -9.32,
          "foot": 2.16,
          "home": -2.24,
          "moto": -0.18,
          "other": 0.34,
          "taxi": 0.0,
          "train_metro": 9.91
        }
      },
      "perc_rank": {
        "2001": {
          "bicycle": 200.0,
          "bus": 129.0,
          "car_van": 155.0,
          "foot": 101.0,
          "home": 281.0,
          "moto": 160.0,
          "other": 288.0,
          "taxi": 145.0,
          "train_metro": 41.0
        },
        "2011": {
          "bicycle": 160.0,
          "bus": 156.0,
          "car_van": 280.0,
          "foot": 59.0,
          "home": 215.0,
          "moto": 121.0,
          "other": 171.0,
          "taxi": 129.0,
          "train_metro": 50.0
        },
        "change": {
          "bicycle": 61.0,
          "bus": 245.0,
          "car_van": 290.0,
          "foot": 51.0,
          "home": 38.0,
          "moto": 96.0,
          "other": 62.0,
          "taxi": 114.0,
          "train_metro": 45.0
        }
      },
      "value": {
        "2001": {
          "all": 49372.0,
          "bicycle": 1010.0,
          "bus": 2793.0,
          "car_van": 32955.0,
          "foot": 5783.0,
          "home": 3261.0,
          "moto": 492.0,
          "other": 117.0,
          "taxi": 228.0,
          "train_metro": 2733.0
        },
        "2011": {
          "all": 47634.0,
          "bicycle": 1087.0,
          "bus": 2271.0,
          "car_van": 27356.0,
          "foot": 6605.0,
          "home": 2075.0,
          "moto": 389.0,
          "other": 276.0,
          "taxi": 217.0,
          "train_metro": 7358.0
        },
        "change": {
          "all": -3.52,
          "bicycle": 7.62,
          "bus": -18.69,
          "car_van": -16.99,
          "foot": 14.21,
          "home": -36.37,
          "moto": -20.93,
          "other": 135.9,
          "taxi": -4.82,
          "train_metro": 169.23
        }
      },
      "value_rank": {
        "2001": {
          "all": 186.0,
          "bicycle": 223.0,
          "bus": 146.0,
          "car_van": 176.0,
          "foot": 164.0,
          "home": 293.0,
          "moto": 196.0,
          "other": 277.0,
          "taxi": 171.0,
          "train_metro": 59.0
        },
        "2011": {
          "all": 252.0,
          "bicycle": 215.0,
          "bus": 188.0,
          "car_van": 279.0,
          "foot": 171.0,
          "home": 281.0,
          "moto": 229.0,
          "other": 242.0,
          "taxi": 198.0,
          "train_metro": 69.0
        },
        "change": {
          "all": 301.0,
          "bicycle": 128.0,
          "bus": 286.0,
          "car_van": 308.0,
          "foot": 198.0,
          "home": 170.0,
          "moto": 222.0,
          "other": 93.0,
          "taxi": 247.0,
          "train_metro": 245.0
        }
      }
    },
    "tenure": {
      "perc": {
        "2001": {
          "owned": 72.39,
          "rent_free": 0.95,
          "rented_private": 9.72,
          "rented_social": 16.15,
          "shared_ownership": 0.79
        },
        "2011": {
          "owned": 61.63,
          "rent_free": 0.79,
          "rented_private": 20.09,
          "rented_social": 16.32,
          "shared_ownership": 1.16
        },
        "change": {
          "owned": -10.76,
          "rent_free": -0.16,
          "rented_private": 10.37,
          "rented_social": 0.17,
          "shared_ownership": 0.37
        }
      },
      "perc_rank": {
        "2001": {
          "owned": 172.0,
          "rent_free": 324.0,
          "rented_private": 124.0,
          "rented_social": 140.0,
          "shared_ownership": 69.0
        },
        "2011": {
          "owned": 262.0,
          "rent_free": 324.0,
          "rented_private": 58.0,
          "rented_social": 117.0,
          "shared_ownership": 40.0
        },
        "change": {
          "owned": 325.0,
          "rent_free": 19.0,
          "rented_private": 18.0,
          "rented_social": 55.0,
          "shared_ownership": 55.0
        }
      },
      "value": {
        "2001": {
          "all": 32608.0,
          "owned": 23605.0,
          "rent_free": 309.0,
          "rented_private": 3170.0,
          "rented_social": 5266.0,
          "shared_ownership": 258.0
        },
        "2011": {
          "all": 36681.0,
          "owned": 22608.0,
          "rent_free": 289.0,
          "rented_private": 7371.0,
          "rented_social": 5987.0,
          "shared_ownership": 426.0
        },
        "change": {
          "all": 12.49,
          "owned": -4.22,
          "rent_free": -6.47,
          "rented_private": 132.52,
          "rented_social": 13.69,
          "shared_ownership": 65.12
        }
      },
      "value_rank": {
        "2001": {
          "all": 289.0,
          "owned": 291.0,
          "rent_free": 324.0,
          "rented_private": 239.0,
          "rented_social": 251.0,
          "shared_ownership": 193.0
        },
        "2011": {
          "all": 279.0,
          "owned": 301.0,
          "rent_free": 323.0,
          "rented_private": 180.0,
          "rented_social": 229.0,
          "shared_ownership": 145.0
        },
        "change": {
          "all": 26.0,
          "owned": 275.0,
          "rent_free": 17.0,
          "rented_private": 36.0,
          "rented_social": 13.0,
          "shared_ownership": 83.0
        }
      }
    },
    "density": {
      "value": {
        "2001": {
          "all": 37.21
        },
        "2011": {
          "all": 42.15
        },
        "change": {
          "all": 13.28
        }
      },
      "value_rank": {
        "2001": {
          "all": 33.0
        },
        "2011": {
          "all": 31.0
        },
        "change": {
          "all": 40.0
        }
      }
    },
    "age10yr": {
      "perc": {
        "2001": {
          "0-9": 13.08,
          "10-19": 11.82,
          "20-29": 15.31,
          "30-39": 18.33,
          "40-49": 13.28,
          "50-59": 10.86,
          "60-69": 7.66,
          "70-79": 3.25,
          "80plus": 6.41
        },
        "2011": {
          "0-9": 13.47,
          "10-19": 11.74,
          "20-29": 15.24,
          "30-39": 17.12,
          "40-49": 14.86,
          "50-59": 10.79,
          "60-69": 7.91,
          "70-79": 2.88,
          "80plus": 5.99
        },
        "change": {
          "0-9": 0.39,
          "10-19": -0.08,
          "20-29": -0.07,
          "30-39": -1.21,
          "40-49": 1.58,
          "50-59": -0.07,
          "60-69": 0.25,
          "70-79": -0.37,
          "80plus": -0.42
        }
      },
      "perc_rank": {
        "2001": {
          "0-9": 59.0,
          "10-19": 287.0,
          "20-29": 41.0,
          "30-39": 19.0,
          "40-49": 209.0,
          "50-59": 290.0,
          "60-69": 300.0,
          "70-79": 294.0,
          "80plus": 279.0
        },
        "2011": {
          "0-9": 28.0,
          "10-19": 235.0,
          "20-29": 61.0,
          "30-39": 24.0,
          "40-49": 174.0,
          "50-59": 295.0,
          "60-69": 302.0,
          "70-79": 300.0,
          "80plus": 296.0
        },
        "change": {
          "0-9": 27.0,
          "10-19": 64.0,
          "20-29": 248.0,
          "30-39": 41.0,
          "40-49": 106.0,
          "50-59": 69.0,
          "60-69": 287.0,
          "70-79": 267.0,
          "80plus": 276.0
        }
      },
      "value": {
        "2001": {
          "0-9": 10426.0,
          "10-19": 9426.0,
          "20-29": 12210.0,
          "30-39": 14614.0,
          "40-49": 10587.0,
          "50-59": 8657.0,
          "60-69": 6106.0,
          "70-79": 2590.0,
          "80plus": 5110.0,
          "all": 79726.0
        },
        "2011": {
          "0-9": 12166.0,
          "10-19": 10600.0,
          "20-29": 13764.0,
          "30-39": 15456.0,
          "40-49": 13422.0,
          "50-59": 9746.0,
          "60-69": 7139.0,
          "70-79": 2600.0,
          "80plus": 5408.0,
          "all": 90301.0
        },
        "change": {
          "0-9": 16.69,
          "10-19": 12.45,
          "20-29": 12.73,
          "30-39": 5.76,
          "40-49": 26.78,
          "50-59": 12.58,
          "60-69": 16.92,
          "70-79": 0.39,
          "80plus": 5.83,
          "all": 13.26
        }
      },
      "value_rank": {
        "2001": {
          "0-9": 265.0,
          "10-19": 294.0,
          "20-29": 188.0,
          "30-39": 235.0,
          "40-49": 295.0,
          "50-59": 315.0,
          "60-69": 314.0,
          "70-79": 316.0,
          "80plus": 307.0,
          "all": 286.0
        },
        "2011": {
          "0-9": 218.0,
          "10-19": 277.0,
          "20-29": 182.0,
          "30-39": 170.0,
          "40-49": 273.0,
          "50-59": 305.0,
          "60-69": 324.0,
          "70-79": 323.0,
          "80plus": 317.0,
          "all": 273.0
        },
        "change": {
          "0-9": 24.0,
          "10-19": 26.0,
          "20-29": 161.0,
          "30-39": 34.0,
          "40-49": 34.0,
          "50-59": 36.0,
          "60-69": 264.0,
          "70-79": 236.0,
          "80plus": 246.0,
          "all": 41.0
        }
      }
    },
    "agemed": {
      "value": {
        "2001": {
          "all": 35.0
        },
        "2011": {
          "all": 35.0
        },
        "change": {
          "all": 0.0
        }
      },
      "value_rank": {
        "2001": {
          "all": 273.0
        },
        "2011": {
          "all": 278.0
        },
        "change": {
          "all": 270.0
        }
      }
    }
  }
}