{
  "code": "E08000026",
  "name": "Coventry",
  "type": "lad",
  "area": 9864.42,
  "count": 331,
  "parents": [
    {
      "code": "E12000005",
      "name": "West Midlands",
      "type": "rgn"
    },
    {
      "code": "E92000001",
      "name": "England",
      "type": "ctry"
    },
    {
      "code": "K04000001",
      "name": "England and Wales",
      "type": "ew"
    }
  ],
  "children": [
    {
      "code": "E02001958",
      "name": "Coventry 001",
      "type": "msoa"
    },
    {
      "code": "E02001959",
      "name": "Coventry 002",
      "type": "msoa"
    },
    {
      "code": "E02001961",
      "name": "Coventry 004",
      "type": "msoa"
    },
    {
      "code": "E02001962",
      "name": "Coventry 005",
      "type": "msoa"
    },
    {
      "code": "E02001963",
      "name": "Coventry 006",
      "type": "msoa"
    },
    {
      "code": "E02001964",
      "name": "Coventry 007",
      "type": "msoa"
    },
    {
      "code": "E02001965",
      "name": "Coventry 008",
      "type": "msoa"
    },
    {
      "code": "E02001966",
      "name": "Coventry 009",
      "type": "msoa"
    },
    {
      "code": "E02001967",
      "name": "Coventry 010",
      "type": "msoa"
    },
    {
      "code": "E02001968",
      "name": "Coventry 011",
      "type": "msoa"
    },
    {
      "code": "E02001969",
      "name": "Coventry 012",
      "type": "msoa"
    },
    {
      "code": "E02001970",
      "name": "Coventry 013",
      "type": "msoa"
    },
    {
      "code": "E02001971",
      "name": "Coventry 014",
      "type": "msoa"
    },
    {
      "code": "E02001972",
      "name": "Coventry 015",
      "type": "msoa"
    },
    {
      "code": "E02001973",
      "name": "Coventry 016",
      "type": "msoa"
    },
    {
      "code": "E02001974",
      "name": "Coventry 017",
      "type": "msoa"
    },
    {
      "code": "E02001975",
      "name": "Coventry 018",
      "type": "msoa"
    },
    {
      "code": "E02001976",
      "name": "Coventry 019",
      "type": "msoa"
    },
    {
      "code": "E02001977",
      "name": "Coventry 020",
      "type": "msoa"
    },
    {
      "code": "E02001978",
      "name": "Coventry 021",
      "type": "msoa"
    },
    {
      "code": "E02001979",
      "name": "Coventry 022",
      "type": "msoa"
    },
    {
      "code": "E02001980",
      "name": "Coventry 023",
      "type": "msoa"
    },
    {
      "code": "E02001981",
      "name": "Coventry 024",
      "type": "msoa"
    },
    {
      "code": "E02001982",
      "name": "Coventry 025",
      "type": "msoa"
    },
    {
      "code": "E02001983",
      "name": "Coventry 026",
      "type": "msoa"
    },
    {
      "code": "E02001984",
      "name": "Coventry 027",
      "type": "msoa"
    },
    {
      "code": "E02001985",
      "name": "Coventry 028",
      "type": "msoa"
    },
    {
      "code": "E02001986",
      "name": "Coventry 029",
      "type": "msoa"
    },
    {
      "code": "E02001987",
      "name": "Coventry 030",
      "type": "msoa"
    },
    {
      "code": "E02001988",
      "name": "Coventry 031",
      "type": "msoa"
    },
    {
      "code": "E02001989",
      "name": "Coventry 032",
      "type": "msoa"
    },
    {
      "code": "E02001990",
      "name": "Coventry 033",
      "type": "msoa"
    },
    {
      "code": "E02001991",
      "name": "Coventry 034",
      "type": "msoa"
    },
    {
      "code": "E02001992",
      "name": "Coventry 035",
      "type": "msoa"
    },
    {
      "code": "E02001993",
      "name": "Coventry 036",
      "type": "msoa"
    },
    {
      "code": "E02001994",
      "name": "Coventry 037",
      "type": "msoa"
    },
    {
      "code": "E02001995",
      "name": "Coventry 038",
      "type": "msoa"
    },
    {
      "code": "E02001996",
      "name": "Coventry 039",
      "type": "msoa"
    },
    {
      "code": "E02001997",
      "name": "Coventry 040",
      "type": "msoa"
    },
    {
      "code": "E02001998",
      "name": "Coventry 041",
      "type": "msoa"
    },
    {
      "code": "E02001999",
      "name": "Coventry 042",
      "type": "msoa"
    },
    {
      "code": "E02006805",
      "name": "Coventry 043",
      "type": "msoa"
    }
  ],
  "bounds": [
    [
      -1.61446,
      52.36388
    ],
    [
      -1.42394,
      52.46478
    ]
  ],
  "data": {
    "population": {
      "perc": {
        "2001": {
          "female": 50.44,
          "male": 49.56
        },
        "2011": {
          "female": 50.27,
          "male": 49.73
        },
        "change": {
          "female": -0.17,
          "male": 0.17
        }
      },
      "perc_rank": {
        "2001": {
          "female": 300.0,
          "male": 32.0
        },
        "2011": {
          "female": 289.0,
          "male": 42.0
        },
        "change": {
          "female": 111.0,
          "male": 217.0
        }
      },
      "value": {
        "2001": {
          "all": 300848.0,
          "female": 151733.0,
          "male": 149115.0
        },
        "2011": {
          "all": 316960.0,
          "female": 159339.0,
          "male": 157621.0
        },
        "change": {
          "all": 5.36,
          "female": 5.01,
          "male": 5.7
        }
      },
      "value_rank": {
        "2001": {
          "all": 28.0,
          "female": 29.0,
          "male": 24.0
        },
        "2011": {
          "all": 27.0,
          "female": 31.0,
          "male": 27.0
        },
        "change": {
          "all": 207.0,
          "female": 190.0,
          "male": 224.0
        }
      }
    },
    "religion": {
      "perc": {
        "2001": {
          "Buddhist": 0.26,
          "Christian": 65.26,
          "Hindu": 2.58,
          "Jewish": 0.07,
          "Muslim": 3.88,
          "No religion": 15.06,
          "Other religion": 0.24,
          "Religion not stated": 7.99,
          "Sikh": 4.64
        },
        "2011": {
          "Buddhist": 0.34,
          "Christian": 53.66,
          "Hindu": 3.52,
          "Jewish": 0.07,
          "Muslim": 7.47,
          "No religion": 23.0,
          "Other religion": 0.52,
          "Religion not stated": 6.41,
          "Sikh": 5.02
        },
        "change": {
          "Buddhist": 0.08,
          "Christian": -11.6,
          "Hindu": 0.94,
          "Jewish": 0.0,
          "Muslim": 3.59,
          "No religion": 7.94,
          "Other religion": 0.28,
          "Religion not stated": -1.58,
          "Sikh": 0.38
        }
      },
      "perc_rank": {
        "2001": {
          "Buddhist": 86.0,
          "Christian": 286.0,
          "Hindu": 22.0,
          "Jewish": 206.0,
          "Muslim": 57.0,
          "No religion": 156.0,
          "Other religion": 172.0,
          "Religion not stated": 92.0,
          "Sikh": 8.0
        },
        "2011": {
          "Buddhist": 131.0,
          "Christian": 280.0,
          "Hindu": 23.0,
          "Jewish": 195.0,
          "Muslim": 46.0,
          "No religion": 232.0,
          "Other religion": 58.0,
          "Religion not stated": 268.0,
          "Sikh": 10.0
        },
        "change": {
          "Buddhist": 247.0,
          "Christian": 115.0,
          "Hindu": 25.0,
          "Jewish": 90.0,
          "Muslim": 28.0,
          "No religion": 290.0,
          "Other religion": 11.0,
          "Religion not stated": 297.0,
          "Sikh": 24.0
        }
      },
      "value": {
        "2001": {
          "Buddhist": 784.0,
          "Christian": 196346.0,
          "Hindu": 7757.0,
          "Jewish": 222.0,
          "Muslim": 11686.0,
          "No religion": 45314.0,
          "Other religion": 733.0,
          "Religion not stated": 24046.0,
          "Sikh": 13960.0,
          "all": 300848.0
        },
        "2011": {
          "Buddhist": 1067.0,
          "Christian": 170090.0,
          "Hindu": 11152.0,
          "Jewish": 210.0,
          "Muslim": 23665.0,
          "No religion": 72896.0,
          "Other religion": 1641.0,
          "Religion not stated": 20327.0,
          "Sikh": 15912.0,
          "all": 316960.0
        },
        "change": {
          "Buddhist": 36.1,
          "Christian": -13.37,
          "Hindu": 43.77,
          "Jewish": -5.41,
          "Muslim": 102.51,
          "No religion": 60.87,
          "Other religion": 123.87,
          "Religion not stated": -15.47,
          "Sikh": 13.98,
          "all": 5.36
        }
      },
      "value_rank": {
        "2001": {
          "Buddhist": 47.0,
          "Christian": 34.0,
          "Hindu": 15.0,
          "Jewish": 114.0,
          "Muslim": 39.0,
          "No religion": 28.0,
          "Other religion": 44.0,
          "Religion not stated": 27.0,
          "Sikh": 6.0,
          "all": 28.0
        },
        "2011": {
          "Buddhist": 56.0,
          "Christian": 35.0,
          "Hindu": 13.0,
          "Jewish": 122.0,
          "Muslim": 36.0,
          "No religion": 41.0,
          "Other religion": 24.0,
          "Religion not stated": 43.0,
          "Sikh": 8.0,
          "all": 27.0
        },
        "change": {
          "Buddhist": 302.0,
          "Christian": 233.0,
          "Hindu": 234.0,
          "Jewish": 178.0,
          "Muslim": 90.0,
          "No religion": 294.0,
          "Other religion": 29.0,
          "Religion not stated": 302.0,
          "Sikh": 252.0,
          "all": 207.0
        }
      }
    },
    "household": {
      "perc": {
        "2001": {
          "CohabitNKids": 5.09,
          "CohabitWKids": 3.57,
          "LoneNKids": 3.64,
          "LoneWKids": 9.28,
          "MarriedNKids": 25.22,
          "MarriedWKids": 17.84,
          "MultiOther": 2.64,
          "MultiStudents": 1.4,
          "OnePerson": 31.31
        },
        "2011": {
          "CohabitNKids": 5.74,
          "CohabitWKids": 4.14,
          "LoneNKids": 4.35,
          "LoneWKids": 10.62,
          "MarriedNKids": 23.03,
          "MarriedWKids": 15.63,
          "MultiOther": 3.14,
          "MultiStudents": 2.13,
          "OnePerson": 31.22
        },
        "change": {
          "CohabitNKids": 0.65,
          "CohabitWKids": 0.57,
          "LoneNKids": 0.71,
          "LoneWKids": 1.34,
          "MarriedNKids": -2.19,
          "MarriedWKids": -2.21,
          "MultiOther": 0.5,
          "MultiStudents": 0.73,
          "OnePerson": -0.09
        }
      },
      "perc_rank": {
        "2001": {
          "CohabitNKids": 245.0,
          "CohabitWKids": 124.0,
          "LoneNKids": 67.0,
          "LoneWKids": 34.0,
          "MarriedNKids": 282.0,
          "MarriedWKids": 232.0,
          "MultiOther": 67.0,
          "MultiStudents": 17.0,
          "OnePerson": 75.0
        },
        "2011": {
          "CohabitNKids": 290.0,
          "CohabitWKids": 201.0,
          "LoneNKids": 52.0,
          "LoneWKids": 22.0,
          "MarriedNKids": 282.0,
          "MarriedWKids": 185.0,
          "MultiOther": 61.0,
          "MultiStudents": 20.0,
          "OnePerson": 94.0
        },
        "change": {
          "CohabitNKids": 266.0,
          "CohabitWKids": 292.0,
          "LoneNKids": 57.0,
          "LoneWKids": 51.0,
          "MarriedNKids": 236.0,
          "MarriedWKids": 115.0,
          "MultiOther": 63.0,
          "MultiStudents": 21.0,
          "OnePerson": 241.0
        }
      },
      "value": {
        "2001": {
          "CohabitNKids": 6224.0,
          "CohabitWKids": 4371.0,
          "LoneNKids": 4454.0,
          "LoneWKids": 11360.0,
          "MarriedNKids": 30858.0,
          "MarriedWKids": 21832.0,
          "MultiOther": 3229.0,
          "MultiStudents": 1713.0,
          "OnePerson": 38312.0,
          "all": 122353.0
        },
        "2011": {
          "CohabitNKids": 7386.0,
          "CohabitWKids": 5321.0,
          "LoneNKids": 5592.0,
          "LoneWKids": 13659.0,
          "MarriedNKids": 29609.0,
          "MarriedWKids": 20097.0,
          "MultiOther": 4044.0,
          "MultiStudents": 2736.0,
          "OnePerson": 40148.0,
          "all": 128592.0
        },
        "change": {
          "CohabitNKids": 18.67,
          "CohabitWKids": 21.73,
          "LoneNKids": 25.55,
          "LoneWKids": 20.24,
          "MarriedNKids": -4.05,
          "MarriedWKids": -7.95,
          "MultiOther": 25.24,
          "MultiStudents": 59.72,
          "OnePerson": 4.79,
          "all": 5.1
        }
      },
      "value_rank": {
        "2001": {
          "CohabitNKids": 44.0,
          "CohabitWKids": 27.0,
          "LoneNKids": 28.0,
          "LoneWKids": 19.0,
          "MarriedNKids": 36.0,
          "MarriedWKids": 33.0,
          "MultiOther": 43.0,
          "MultiStudents": 12.0,
          "OnePerson": 29.0,
          "all": 28.0
        },
        "2011": {
          "CohabitNKids": 55.0,
          "CohabitWKids": 41.0,
          "LoneNKids": 27.0,
          "LoneWKids": 17.0,
          "MarriedNKids": 40.0,
          "MarriedWKids": 41.0,
          "MultiOther": 39.0,
          "MultiStudents": 14.0,
          "OnePerson": 31.0,
          "all": 32.0
        },
        "change": {
          "CohabitNKids": 264.0,
          "CohabitWKids": 304.0,
          "LoneNKids": 148.0,
          "LoneWKids": 171.0,
          "MarriedNKids": 300.0,
          "MarriedWKids": 169.0,
          "MultiOther": 106.0,
          "MultiStudents": 150.0,
          "OnePerson": 262.0,
          "all": 261.0
        }
      }
    },
    "ethnicity": {
      "perc": {
        "2001": {
          "asian": 12.0,
          "black": 1.8,
          "mixed": 1.72,
          "other": 0.51,
          "white": 83.98
        },
        "2011": {
          "asian": 16.28,
          "black": 5.6,
          "mixed": 2.6,
          "other": 1.68,
          "white": 73.84
        },
        "change": {
          "asian": 4.28,
          "black": 3.8,
          "mixed": 0.88,
          "other": 1.17,
          "white": -10.14
        }
      },
      "perc_rank": {
        "2001": {
          "asian": 25.0,
          "black": 48.0,
          "mixed": 54.0,
          "other": 50.0,
          "white": 296.0
        },
        "2011": {
          "asian": 27.0,
          "black": 42.0,
          "mixed": 63.0,
          "other": 37.0,
          "white": 293.0
        },
        "change": {
          "asian": 42.0,
          "black": 10.0,
          "mixed": 95.0,
          "other": 32.0,
          "white": 306.0
        }
      },
      "value": {
        "2001": {
          "all": 300848.0,
          "asian": 36093.0,
          "black": 5412.0,
          "mixed": 5163.0,
          "other": 1537.0,
          "white": 252643.0
        },
        "2011": {
          "all": 316960.0,
          "asian": 51598.0,
          "black": 17764.0,
          "mixed": 8230.0,
          "other": 5339.0,
          "white": 234029.0
        },
        "change": {
          "all": 5.36,
          "asian": 42.96,
          "black": 228.23,
          "mixed": 59.4,
          "other": 247.36,
          "white": -7.37
        }
      },
      "value_rank": {
        "2001": {
          "all": 28.0,
          "asian": 16.0,
          "black": 42.0,
          "mixed": 40.0,
          "other": 35.0,
          "white": 32.0
        },
        "2011": {
          "all": 27.0,
          "asian": 21.0,
          "black": 35.0,
          "mixed": 45.0,
          "other": 32.0,
          "white": 40.0
        },
        "change": {
          "all": 207.0,
          "asian": 311.0,
          "black": 48.0,
          "mixed": 312.0,
          "other": 49.0,
          "white": 315.0
        }
      }
    },
    "health": {
      "perc": {
        "2001": {
          "bad": 9.97,
          "fair": 22.63,
          "good": 67.41
        },
        "2011": {
          "bad": 6.05,
          "fair": 13.25,
          "good": 80.69
        },
        "change": {
          "bad": -3.92,
          "fair": -9.38,
          "good": 13.28
        }
      },
      "perc_rank": {
        "2001": {
          "bad": 96.0,
          "fair": 137.0,
          "good": 214.0
        },
        "2011": {
          "bad": 102.0,
          "fair": 178.0,
          "good": 191.0
        },
        "change": {
          "bad": 238.0,
          "fair": 238.0,
          "good": 56.0
        }
      },
      "value": {
        "2001": {
          "all": 300848.0,
          "bad": 29988.0,
          "fair": 68070.0,
          "good": 202790.0
        },
        "2011": {
          "all": 316960.0,
          "bad": 19191.0,
          "fair": 42006.0,
          "good": 255763.0
        },
        "change": {
          "all": 5.36,
          "bad": -36.0,
          "fair": -38.29,
          "good": 26.12
        }
      },
      "value_rank": {
        "2001": {
          "all": 28.0,
          "bad": 26.0,
          "fair": 23.0,
          "good": 26.0
        },
        "2011": {
          "all": 27.0,
          "bad": 30.0,
          "fair": 30.0,
          "good": 30.0
        },
        "change": {
          "all": 207.0,
          "bad": 205.0,
          "fair": 231.0,
          "good": 148.0
        }
      }
    },
    "economic": {
      "perc": {
        "2001": {
          "employee": 50.29,
          "inactive": 36.89,
          "self-employed": 5.16,
          "student": 3.7,
          "unemployed": 3.96
        },
        "2011": {
          "employee": 49.35,
          "inactive": 33.69,
          "self-employed": 6.18,
          "student": 5.37,
          "unemployed": 5.4
        },
        "change": {
          "employee": -0.94,
          "inactive": -3.2,
          "self-employed": 1.02,
          "student": 1.67,
          "unemployed": 1.44
        }
      },
      "perc_rank": {
        "2001": {
          "employee": 231.0,
          "inactive": 66.0,
          "self-employed": 306.0,
          "student": 27.0,
          "unemployed": 65.0
        },
        "2011": {
          "employee": 267.0,
          "inactive": 49.0,
          "self-employed": 310.0,
          "student": 24.0,
          "unemployed": 46.0
        },
        "change": {
          "employee": 218.0,
          "inactive": 212.0,
          "self-employed": 224.0,
          "student": 23.0,
          "unemployed": 50.0
        }
      },
      "value": {
        "2001": {
          "all": 214833.0,
          "employee": 108036.0,
          "inactive": 79257.0,
          "self-employed": 11092.0,
          "student": 7943.0,
          "unemployed": 8505.0
        },
        "2011": {
          "all": 231871.0,
          "employee": 114424.0,
          "inactive": 78126.0,
          "self-employed": 14340.0,
          "student": 12449.0,
          "unemployed": 12532.0
        },
        "change": {
          "all": 7.93,
          "employee": 5.91,
          "inactive": -1.43,
          "self-employed": 29.28,
          "student": 56.73,
          "unemployed": 47.35
        }
      },
      "value_rank": {
        "2001": {
          "all": 28.0,
          "employee": 34.0,
          "inactive": 23.0,
          "self-employed": 76.0,
          "student": 11.0,
          "unemployed": 32.0
        },
        "2011": {
          "all": 31.0,
          "employee": 34.0,
          "inactive": 20.0,
          "self-employed": 75.0,
          "student": 13.0,
          "unemployed": 28.0
        },
        "change": {
          "all": 161.0,
          "employee": 209.0,
          "inactive": 179.0,
          "self-employed": 97.0,
          "student": 52.0,
          "unemployed": 161.0
        }
      }
    },
    "travel": {
      "perc": {
        "2001": {
          "bicycle": 2.48,
          "bus": 10.68,
          "car_van": 69.41,
          "foot": 9.28,
          "home": 5.76,
          "moto": 0.78,
          "other": 0.24,
          "taxi": 0.45,
          "train_metro": 0.92
        },
        "2011": {
          "bicycle": 2.66,
          "bus": 11.06,
          "car_van": 67.41,
          "foot": 11.58,
          "home": 3.2,
          "moto": 0.63,
          "other": 0.63,
          "taxi": 0.6,
          "train_metro": 2.25
        },
        "change": {
          "bicycle": 0.18,
          "bus": 0.38,
          "car_van": -2.0,
          "foot": 2.3,
          "home": -2.56,
          "moto": -0.15,
          "other": 0.39,
          "taxi": 0.15,
          "train_metro": 1.33
        }
      },
      "perc_rank": {
        "2001": {
          "bicycle": 164.0,
          "bus": 43.0,
          "car_van": 84.0,
          "foot": 224.0,
          "home": 307.0,
          "moto": 278.0,
          "other": 288.0,
          "taxi": 151.0,
          "train_metro": 168.0
        },
        "2011": {
          "bicycle": 126.0,
          "bus": 45.0,
          "car_van": 198.0,
          "foot": 108.0,
          "home": 298.0,
          "moto": 233.0,
          "other": 129.0,
          "taxi": 85.0,
          "train_metro": 188.0
        },
        "change": {
          "bicycle": 66.0,
          "bus": 101.0,
          "car_van": 237.0,
          "foot": 48.0,
          "home": 46.0,
          "moto": 80.0,
          "other": 39.0,
          "taxi": 44.0,
          "train_metro": 190.0
        }
      },
      "value": {
        "2001": {
          "all": 141971.0,
          "bicycle": 3522.0,
          "bus": 15159.0,
          "car_van": 98544.0,
          "foot": 13177.0,
          "home": 8181.0,
          "moto": 1106.0,
          "other": 338.0,
          "taxi": 644.0,
          "train_metro": 1300.0
        },
        "2011": {
          "all": 137560.0,
          "bicycle": 3658.0,
          "bus": 15215.0,
          "car_van": 92725.0,
          "foot": 15930.0,
          "home": 4397.0,
          "moto": 860.0,
          "other": 861.0,
          "taxi": 820.0,
          "train_metro": 3094.0
        },
        "change": {
          "all": -3.11,
          "bicycle": 3.86,
          "bus": 0.37,
          "car_van": -5.9,
          "foot": 20.89,
          "home": -46.25,
          "moto": -22.24,
          "other": 154.73,
          "taxi": 27.33,
          "train_metro": 138.0
        }
      },
      "value_rank": {
        "2001": {
          "all": 26.0,
          "bicycle": 40.0,
          "bus": 18.0,
          "car_van": 20.0,
          "foot": 30.0,
          "home": 70.0,
          "moto": 53.0,
          "other": 61.0,
          "taxi": 51.0,
          "train_metro": 110.0
        },
        "2011": {
          "all": 37.0,
          "bicycle": 55.0,
          "bus": 33.0,
          "car_van": 31.0,
          "foot": 35.0,
          "home": 121.0,
          "moto": 68.0,
          "other": 50.0,
          "taxi": 39.0,
          "train_metro": 140.0
        },
        "change": {
          "all": 298.0,
          "bicycle": 154.0,
          "bus": 210.0,
          "car_van": 285.0,
          "foot": 131.0,
          "home": 264.0,
          "moto": 228.0,
          "other": 66.0,
          "taxi": 89.0,
          "train_metro": 260.0
        }
      }
    },
    "tenure": {
      "perc": {
        "2001": {
          "owned": 68.73,
          "rent_free": 2.39,
          "rented_private": 10.09,
          "rented_social": 18.12,
          "shared_ownership": 0.67
        },
        "2011": {
          "owned": 60.56,
          "rent_free": 1.2,
          "rented_private": 20.61,
          "rented_social": 17.04,
          "shared_ownership": 0.58
        },
        "change": {
          "owned": -8.17,
          "rent_free": -1.19,
          "rented_private": 10.52,
          "rented_social": -1.08,
          "shared_ownership": -0.09
        }
      },
      "perc_rank": {
        "2001": {
          "owned": 240.0,
          "rent_free": 84.0,
          "rented_private": 110.0,
          "rented_social": 110.0,
          "shared_ownership": 105.0
        },
        "2011": {
          "owned": 266.0,
          "rent_free": 203.0,
          "rented_private": 55.0,
          "rented_social": 108.0,
          "shared_ownership": 193.0
        },
        "change": {
          "owned": 303.0,
          "rent_free": 306.0,
          "rented_private": 16.0,
          "rented_social": 200.0,
          "shared_ownership": 276.0
        }
      },
      "value": {
        "2001": {
          "all": 123174.0,
          "owned": 84661.0,
          "rent_free": 2946.0,
          "rented_private": 12429.0,
          "rented_social": 22317.0,
          "shared_ownership": 821.0
        },
        "2011": {
          "all": 128592.0,
          "owned": 77880.0,
          "rent_free": 1545.0,
          "rented_private": 26503.0,
          "rented_social": 21914.0,
          "shared_ownership": 750.0
        },
        "change": {
          "all": 4.4,
          "owned": -8.01,
          "rent_free": -47.56,
          "rented_private": 113.24,
          "rented_social": -1.81,
          "shared_ownership": -8.65
        }
      },
      "value_rank": {
        "2001": {
          "all": 28.0,
          "owned": 30.0,
          "rent_free": 27.0,
          "rented_private": 41.0,
          "rented_social": 50.0,
          "shared_ownership": 36.0
        },
        "2011": {
          "all": 32.0,
          "owned": 33.0,
          "rent_free": 47.0,
          "rented_private": 33.0,
          "rented_social": 51.0,
          "shared_ownership": 61.0
        },
        "change": {
          "all": 267.0,
          "owned": 306.0,
          "rent_free": 326.0,
          "rented_private": 73.0,
          "rented_social": 225.0,
          "shared_ownership": 270.0
        }
      }
    },
    "density": {
      "value": {
        "2001": {
          "all": 30.5
        },
        "2011": {
          "all": 32.13
        },
        "change": {
          "all": 5.34
        }
      },
      "value_rank": {
        "2001": {
          "all": 49.0
        },
        "2011": {
          "all": 54.0
        },
        "change": {
          "all": 211.0
        }
      }
    },
    "age10yr": {
      "perc": {
        "2001": {
          "0-9": 12.87,
          "10-19": 14.33,
          "20-29": 15.0,
          "30-39": 14.73,
          "40-49": 12.35,
          "50-59": 10.84,
          "60-69": 8.68,
          "70-79": 3.77,
          "80plus": 7.43
        },
        "2011": {
          "0-9": 12.9,
          "10-19": 13.27,
          "20-29": 17.5,
          "30-39": 13.31,
          "40-49": 13.11,
          "50-59": 10.47,
          "60-69": 9.01,
          "70-79": 3.41,
          "80plus": 7.02
        },
        "change": {
          "0-9": 0.03,
          "10-19": -1.06,
          "20-29": 2.5,
          "30-39": -1.42,
          "40-49": 0.76,
          "50-59": -0.37,
          "60-69": 0.33,
          "70-79": -0.36,
          "80plus": -0.41
        }
      },
      "perc_rank": {
        "2001": {
          "0-9": 80.0,
          "10-19": 18.0,
          "20-29": 45.0,
          "30-39": 219.0,
          "40-49": 301.0,
          "50-59": 292.0,
          "60-69": 252.0,
          "70-79": 234.0,
          "80plus": 183.0
        },
        "2011": {
          "0-9": 47.0,
          "10-19": 19.0,
          "20-29": 35.0,
          "30-39": 96.0,
          "40-49": 313.0,
          "50-59": 302.0,
          "60-69": 278.0,
          "70-79": 264.0,
          "80plus": 251.0
        },
        "change": {
          "0-9": 52.0,
          "10-19": 264.0,
          "20-29": 24.0,
          "30-39": 49.0,
          "40-49": 277.0,
          "50-59": 121.0,
          "60-69": 283.0,
          "70-79": 263.0,
          "80plus": 274.0
        }
      },
      "value": {
        "2001": {
          "0-9": 38713.0,
          "10-19": 43124.0,
          "20-29": 45139.0,
          "30-39": 44300.0,
          "40-49": 37166.0,
          "50-59": 32607.0,
          "60-69": 26106.0,
          "70-79": 11352.0,
          "80plus": 22341.0,
          "all": 300848.0
        },
        "2011": {
          "0-9": 40878.0,
          "10-19": 42073.0,
          "20-29": 55458.0,
          "30-39": 42197.0,
          "40-49": 41563.0,
          "50-59": 33185.0,
          "60-69": 28564.0,
          "70-79": 10807.0,
          "80plus": 22235.0,
          "all": 316960.0
        },
        "change": {
          "0-9": 5.59,
          "10-19": -2.44,
          "20-29": 22.86,
          "30-39": -4.75,
          "40-49": 11.83,
          "50-59": 1.77,
          "60-69": 9.42,
          "70-79": -4.8,
          "80plus": -0.47,
          "all": 5.36
        }
      },
      "value_rank": {
        "2001": {
          "0-9": 21.0,
          "10-19": 14.0,
          "20-29": 23.0,
          "30-39": 33.0,
          "40-49": 35.0,
          "50-59": 35.0,
          "60-69": 32.0,
          "70-79": 31.0,
          "80plus": 26.0,
          "all": 28.0
        },
        "2011": {
          "0-9": 22.0,
          "10-19": 19.0,
          "20-29": 22.0,
          "30-39": 41.0,
          "40-49": 41.0,
          "50-59": 40.0,
          "60-69": 39.0,
          "70-79": 35.0,
          "80plus": 34.0,
          "all": 27.0
        },
        "change": {
          "0-9": 87.0,
          "10-19": 257.0,
          "20-29": 57.0,
          "30-39": 74.0,
          "40-49": 272.0,
          "50-59": 167.0,
          "60-69": 297.0,
          "70-79": 282.0,
          "80plus": 290.0,
          "all": 207.0
        }
      }
    },
    "agemed": {
      "value": {
        "2001": {
          "all": 35.0
        },
        "2011": {
          "all": 34.0
        },
        "change": {
          "all": -2.86
        }
      },
      "value_rank": {
        "2001": {
          "all": 273.0
        },
        "2011": {
          "all": 293.0
        },
        "change": {
          "all": 307.0
        }
      }
    }
  }
}